{
  "version": "1.0.0",
  "lastScanned": 1773273891226,
  "projectRoot": "/Users/invaiz/Documents/develop/dayzero_B2C/dayzero-app",
  "techStack": {
    "languages": [
      {
        "name": "JavaScript/TypeScript",
        "version": null,
        "confidence": "high",
        "markers": [
          "package.json"
        ]
      },
      {
        "name": "TypeScript",
        "version": null,
        "confidence": "high",
        "markers": [
          "tsconfig.json"
        ]
      }
    ],
    "frameworks": [
      {
        "name": "react",
        "version": "19.2.0",
        "category": "frontend"
      },
      {
        "name": "react-dom",
        "version": "19.2.0",
        "category": "frontend"
      },
      {
        "name": "vite",
        "version": "7.3.1",
        "category": "build"
      }
    ],
    "packageManager": "npm",
    "runtime": null
  },
  "build": {
    "buildCommand": "npm run build",
    "testCommand": null,
    "lintCommand": "npm run lint",
    "devCommand": "npm run dev",
    "scripts": {
      "dev": "vite",
      "build": "tsc -b && vite build",
      "lint": "eslint .",
      "preview": "vite preview"
    }
  },
  "conventions": {
    "namingStyle": null,
    "importStyle": null,
    "testPattern": null,
    "fileOrganization": "type-based"
  },
  "structure": {
    "isMonorepo": false,
    "workspaces": [],
    "mainDirectories": [
      "public",
      "src"
    ],
    "gitBranches": {
      "defaultBranch": "main",
      "branchingStrategy": null
    }
  },
  "customNotes": [],
  "directoryMap": {
    "dist": {
      "path": "dist",
      "purpose": "Distribution/build output",
      "fileCount": 5,
      "lastAccessed": 1773273891205,
      "keyFiles": [
        "DayZero Logo.png",
        "Qoo10.png",
        "dayzero-logo.png",
        "index.html",
        "vite.svg"
      ]
    },
    "public": {
      "path": "public",
      "purpose": "Public files",
      "fileCount": 4,
      "lastAccessed": 1773273891206,
      "keyFiles": [
        "DayZero Logo.png",
        "Qoo10.png",
        "dayzero-logo.png",
        "vite.svg"
      ]
    },
    "src": {
      "path": "src",
      "purpose": "Source code",
      "fileCount": 4,
      "lastAccessed": 1773273891206,
      "keyFiles": [
        "App.css",
        "App.tsx",
        "index.css",
        "main.tsx"
      ]
    },
    "dist/assets": {
      "path": "dist/assets",
      "purpose": "Static assets",
      "fileCount": 2,
      "lastAccessed": 1773273891207,
      "keyFiles": [
        "index-Bjxh_95e.css",
        "index-ClZtN7fj.js"
      ]
    },
    "src/assets": {
      "path": "src/assets",
      "purpose": "Static assets",
      "fileCount": 1,
      "lastAccessed": 1773273891207,
      "keyFiles": [
        "react.svg"
      ]
    },
    "src/components": {
      "path": "src/components",
      "purpose": "UI components",
      "fileCount": 0,
      "lastAccessed": 1773273891208,
      "keyFiles": []
    },
    "src/pages": {
      "path": "src/pages",
      "purpose": "Page components",
      "fileCount": 1,
      "lastAccessed": 1773273891208,
      "keyFiles": [
        "SourcingPage.tsx"
      ]
    }
  },
  "hotPaths": [
    {
      "path": "src/pages/editing/tabs/PriceEditTab.tsx",
      "accessCount": 172,
      "lastAccessed": 1773330400716,
      "type": "file"
    },
    {
      "path": "src/pages/editing/tabs/BasicEditTab.tsx",
      "accessCount": 136,
      "lastAccessed": 1773325254816,
      "type": "file"
    },
    {
      "path": "src/pages/editing/components/ProductListItem.tsx",
      "accessCount": 42,
      "lastAccessed": 1773329942835,
      "type": "file"
    },
    {
      "path": "src/pages/editing/components/EditingHeader.tsx",
      "accessCount": 36,
      "lastAccessed": 1773328814969,
      "type": "file"
    },
    {
      "path": "src/pages/editing/EditingListPage.tsx",
      "accessCount": 36,
      "lastAccessed": 1773328839972,
      "type": "directory"
    },
    {
      "path": "src/store/useEditingStore.ts",
      "accessCount": 35,
      "lastAccessed": 1773330389612,
      "type": "file"
    },
    {
      "path": "src/mock/editingMock.ts",
      "accessCount": 32,
      "lastAccessed": 1773330301189,
      "type": "file"
    },
    {
      "path": "src/pages/editing",
      "accessCount": 28,
      "lastAccessed": 1773325264684,
      "type": "directory"
    },
    {
      "path": "src/pages/onboarding/BasicMarginPage.tsx",
      "accessCount": 26,
      "lastAccessed": 1773328630042,
      "type": "file"
    },
    {
      "path": "src",
      "accessCount": 25,
      "lastAccessed": 1773329144730,
      "type": "directory"
    },
    {
      "path": "src/pages/editing/tabs/DetailImageEditTab.tsx",
      "accessCount": 21,
      "lastAccessed": 1773325160856,
      "type": "file"
    },
    {
      "path": "src/pages/editing/tabs/ThumbnailEditTab.tsx",
      "accessCount": 20,
      "lastAccessed": 1773325232224,
      "type": "file"
    },
    {
      "path": "src/pages/editing/EditingDetailPage.tsx",
      "accessCount": 18,
      "lastAccessed": 1773330361874,
      "type": "file"
    },
    {
      "path": "src/pages/editing/components/BulkActionBar.tsx",
      "accessCount": 17,
      "lastAccessed": 1773323302506,
      "type": "file"
    },
    {
      "path": "src/pages/editing/components/EditingTabBar.tsx",
      "accessCount": 15,
      "lastAccessed": 1773323299128,
      "type": "file"
    },
    {
      "path": "src/design/tokens.ts",
      "accessCount": 14,
      "lastAccessed": 1773329693092,
      "type": "file"
    },
    {
      "path": "src/pages/sourcing/components/UrlSourcingContent.tsx",
      "accessCount": 14,
      "lastAccessed": 1773330319594,
      "type": "file"
    },
    {
      "path": "src/types/editing.ts",
      "accessCount": 13,
      "lastAccessed": 1773329154455,
      "type": "file"
    },
    {
      "path": "src/pages/editing/components/TranslationModal.tsx",
      "accessCount": 11,
      "lastAccessed": 1773323302276,
      "type": "file"
    },
    {
      "path": "src/components/common/NotificationPanel.tsx",
      "accessCount": 5,
      "lastAccessed": 1773302349285,
      "type": "file"
    },
    {
      "path": "src/components/onboarding/OnboardingContext.tsx",
      "accessCount": 4,
      "lastAccessed": 1773293341322,
      "type": "file"
    },
    {
      "path": "src/mock/detailImageSvgs.ts",
      "accessCount": 3,
      "lastAccessed": 1773305023627,
      "type": "file"
    },
    {
      "path": "src/mock/categoryMap.ts",
      "accessCount": 2,
      "lastAccessed": 1773281421997,
      "type": "directory"
    },
    {
      "path": "",
      "accessCount": 2,
      "lastAccessed": 1773319469437,
      "type": "directory"
    },
    {
      "path": "src/mock",
      "accessCount": 1,
      "lastAccessed": 1773273983661,
      "type": "directory"
    },
    {
      "path": "src/pages/sourcing",
      "accessCount": 1,
      "lastAccessed": 1773276182267,
      "type": "directory"
    },
    {
      "path": "src/components/common/ConfirmModal.tsx",
      "accessCount": 1,
      "lastAccessed": 1773276376253,
      "type": "file"
    },
    {
      "path": "src/components/onboarding",
      "accessCount": 1,
      "lastAccessed": 1773282661797,
      "type": "directory"
    },
    {
      "path": "src/pages/onboarding",
      "accessCount": 1,
      "lastAccessed": 1773282671179,
      "type": "directory"
    },
    {
      "path": "src/components/layout/MainLayout.tsx",
      "accessCount": 1,
      "lastAccessed": 1773289677966,
      "type": "file"
    },
    {
      "path": "src/index.css",
      "accessCount": 1,
      "lastAccessed": 1773289766662,
      "type": "file"
    },
    {
      "path": "src/App.css",
      "accessCount": 1,
      "lastAccessed": 1773289815175,
      "type": "file"
    },
    {
      "path": "src/pages/editing/tabs",
      "accessCount": 1,
      "lastAccessed": 1773291326438,
      "type": "directory"
    },
    {
      "path": "src/types/sourcing.ts",
      "accessCount": 1,
      "lastAccessed": 1773317693307,
      "type": "file"
    },
    {
      "path": "src/store",
      "accessCount": 1,
      "lastAccessed": 1773319502096,
      "type": "directory"
    },
    {
      "path": "reviews/2026-03-12-ED-editing-review.md",
      "accessCount": 1,
      "lastAccessed": 1773319871048,
      "type": "file"
    },
    {
      "path": "src/pages/editing/components/CollectionProgressBanner.tsx",
      "accessCount": 1,
      "lastAccessed": 1773323302910,
      "type": "file"
    },
    {
      "path": "src/utils/editing.ts",
      "accessCount": 1,
      "lastAccessed": 1773325049516,
      "type": "file"
    },
    {
      "path": "src/components/common",
      "accessCount": 1,
      "lastAccessed": 1773329700229,
      "type": "directory"
    }
  ],
  "userDirectives": []
}